newmonkey-1.0.2.dist-info/METADATA
newmonkey-1.0.2.dist-info/WHEEL
newmonkey-1.0.2.dist-info/entry_points.txt
newmonkey-1.0.2.dist-info/licenses/LICENCE
newmonkey/__init__.py
newmonkey/__main__.py
newmonkey/cli.py
newmonkey/main.py
newmonkey/parsing.py
newmonkey-1.0.2.dist-info/RECORD
