Metadata-Version: 2.1
Name: newmonkey
Version: 1.0.2
Summary: A cli tool to convert your discord cache back to the original files.
Author: CallMePixelMan
License: MIT
Project-URL: Homepage, https://github.com/CallMePixelMan/newmonkey
Requires-Python: >=3.11
Requires-Dist: python-magic>=0.4.27
